pysls/__init__.py
pysls/src/create/create_lambda.py
pysls/src/create/create_layer.py
pysls/src/events/event_mapping.json
pysls/src/events/generate_event.py
pysls/src/events/model_files/alexa-skills-kit/AlexaEndSession.json
pysls/src/events/model_files/alexa-skills-kit/AlexaIntentAnswer.json
pysls/src/events/model_files/alexa-skills-kit/AlexaIntentGetNewFact.json
pysls/src/events/model_files/alexa-skills-kit/AlexaIntentMyColorIs.json
pysls/src/events/model_files/alexa-skills-kit/AlexaIntentRecipe.json
pysls/src/events/model_files/alexa-skills-kit/AlexaStartSession.json
pysls/src/events/model_files/alexa-smart-home/AlexaSmartHomeControlTurnOffRequest.json
pysls/src/events/model_files/alexa-smart-home/AlexaSmartHomeControlTurnOnRequest.json
pysls/src/events/model_files/alexa-smart-home/AlexaSmartHomeDiscoveryRequest.json
pysls/src/events/model_files/apigateway/ApiGatewayAuthorizer.json
pysls/src/events/model_files/apigateway/AwsProxy.json
pysls/src/events/model_files/batch/BatchGetJob.json
pysls/src/events/model_files/batch/BatchSubmitJob.json
pysls/src/events/model_files/cloudformation/CfnCreateRequest.json
pysls/src/events/model_files/cloudfront/CloudFrontABTest.json
pysls/src/events/model_files/cloudfront/CloudFrontAccessRequestInResponse.json
pysls/src/events/model_files/cloudfront/CloudFrontHttpRedirect.json
pysls/src/events/model_files/cloudfront/CloudFrontModifyQueryString.json
pysls/src/events/model_files/cloudfront/CloudFrontModifyResponseHeader.json
pysls/src/events/model_files/cloudfront/CloudFrontMultipleRemoteCallsAggregateResponse.json
pysls/src/events/model_files/cloudfront/CloudFrontNormalizeQuerystringToImproveCacheHit.json
pysls/src/events/model_files/cloudfront/CloudFrontRedirectOnViewerCountry.json
pysls/src/events/model_files/cloudfront/CloudFrontRedirectUnauthenticatedUsers.json
pysls/src/events/model_files/cloudfront/CloudFrontResponseGeneration.json
pysls/src/events/model_files/cloudfront/CloudFrontServeObjectOnViewerDevice.json
pysls-1.2.0.dist-info/entry_points.txt
pysls-1.2.0.dist-info/LICENSE
pysls-1.2.0.dist-info/WHEEL
pysls-1.2.0.dist-info/METADATA
pysls-1.2.0.dist-info/RECORD
