Metadata-Version: 2.1
Name: pysls
Version: 1.2.0
Summary: 
Home-page: https://github.com/LucasFDutra/pysls
Author: LucasFDutra
Requires-Python: >=3.8,<4.0
Classifier: Programming Language :: Python :: 3
Classifier: Programming Language :: Python :: 3.8
Classifier: Programming Language :: Python :: 3.9
Requires-Dist: boto3 (>=1.15.16,<2.0.0)
